pywol/__init__.py
pywol/cli.py
pywol/wol.py
pywol-1.0.0.dist-info/LICENSE
pywol-1.0.0.dist-info/METADATA
pywol-1.0.0.dist-info/WHEEL
pywol-1.0.0.dist-info/entry_points.txt
pywol-1.0.0.dist-info/top_level.txt
pywol-1.0.0.dist-info/RECORD
