Metadata-Version: 2.1
Name: pywol
Version: 1.0.0
Summary: A Wake-on-LAN tool written in Python.
Home-page: https://github.com/erberlin/pywol
Author: Erik R Berlin
Author-email: erberlin.dev@gmail.com
License: MIT
Platform: UNKNOWN
Classifier: License :: OSI Approved :: MIT License
Classifier: Programming Language :: Python :: 3
Classifier: Programming Language :: Python :: 3.6
Classifier: Programming Language :: Python :: 3.7
Requires-Python: >=3.6
Requires-Dist: Click
